{"DELETION OF INTEREST": {"72": null, "10521": null, "13": null, "89": null, "1": null, "2239": null, "67": null, "8671": null, "82": null, "76": null, "34571": null, "23977": null, "34574": null, "62988": null, "281": null, "12069": null, "64590": null, "12079": null, "4": null, "66": null, "2242": null, "78": null, "23904": null, "324": null, "30": null, "16": null, "11": null, "289": null, "294": null, "4773": null, "338": null, "342": null, "2248": null, "33243": null, "83": null, "12667": null, "20148": null, "40412": null, "8654": null, "55872": null, "40416": null, "10518": null, "38234": null, "12760": null, "41434": null, "273": null, "3666": null, "40406": null, "286": null, "42886": null, "20710": null, "23552": null, "17376": null, "14357": null, "213": null, "22612": null, "18561": null, "1701": null, "71": null, "90626": null, "52": null, "39359": null, "59519": null, "28539": null, "298": null, "2367": null, "47256": null, "4781": null, "47776": null, "348": null, "23971": null, "23563": null, "23550": null, "10133": null, "283": null, "20709": null, "26242": null, "59919": null, "105691": null, "132997": null, "176675": null, "26187": null, "1724": null, "278": null, "40405": null, "23555": null, "4477": null, "37085": null, "38237": null, "62990": null, "19888": null, "10457": null, "20144": null, "36627": null, "14753": null, "1081": null, "39088": null, "64724": null, "79476": null, "119494": null}, "POLICY CHANGE": {"1336": null, "50824": null, "482": null, "1389": null, "14001": null, "126360": null, "14293": null, "5816": null, "1407": null, "20326": null, "21704": null, "5535": null, "9172": null, "1376": null, "2704": null, "7108": null, "14359": null, "14284": null, "9358": null, "20323": null, "20327": null, "2713": null, "19329": null, "3817": null, "14355": null, "12987": null, "1875": null, "14361": null, "20322": null, "11780": null, "14369": null, "3813": null, "9177": null, "9179": null, "9180": null, "24625": null, "2712": null, "19328": null, "20311": null, "14007": null, "5828": null, "5633": null, "9176": null, "14639": null, "58758": null, "2770": null, "60407": null, "13962": null, "98": null, "2748": null, "30385": null, "2659": null, "2651": null, "2448": null, "9167": null, "9162": null, "9170": null, "9171": null, "8624": null, "1591": null, "2741": null, "4479": null, "546": null, "2477": null, "104": null, "1956": null, "2444": null, "19319": null, "59172": null, "283": null, "3867": null, "2601": null, "14602": null, "2463": null, "2453": null, "9163": null, "30914": null, "3816": null, "1926": null, "3489": null, "8642": null, "20453": null, "1919": null, "5648": null, "24406": null, "3253": null, "2718": null, "2680": null, "11791": null, "20482": null, "10948": null, "14357": null, "5650": null, "14341": null, "24627": null, "28645": null, "105": null, "226": null, "3823": null, "1444": null}, "CANCELLATION NOTICE": {"2288": null, "281": null, "33030": null, "33031": null, "2242": null, "273": null, "33047": null, "13292": null, "14769": null, "278": null, "286": null, "28539": null, "2847": null, "280": null, "47239": null, "2239": null, "3781": null, "3739": null, "2115": null, "2289": null, "283": null, "1941": null, "226": null, "2367": null, "19888": null, "22599": null, "2283": null, "7695": null, "12822": null, "59904": null, "2252": null, "7686": null, "33033": null, "19721": null, "213": null, "1": null, "71524": null, "1849": null, "3736": null, "7521": null, "10457": null, "272": null, "3666": null, "2205": null, "3412": null, "29550": null, "33024": null, "5769": null, "7299": null, "14762": null, "128000": null, "3601": null, "33034": null, "16451": null, "7672": null, "9206": null, "5728": null, "7273": null, "5734": null, "5760": null, "7513": null, "25937": null, "855": null, "31051": null, "40470": null, "12818": null, "14772": null, "13769": null, "33028": null, "271": null, "3740": null, "10439": null, "33029": null, "33045": null, "11253": null, "2286": null, "2418": null, "11260": null, "66": null, "46271": null, "51735": null, "24075": null, "7268": null, "7400": null, "181650": null, "7667": null, "19988": null, "59903": null, "71866": null, "1669": null, "2282": null, "20961": null, "42317": null, "148470": null, "46504": null, "88174": null, "45269": null, "7643": null, "3729": null, "2085": null}, "EXPIRATION NOTICE": {"30264": null, "7686": null, "7565": null, "33212": null, "33213": null, "32352": null, "33221": null, "37685": null, "7672": null, "19772": null, "7695": null, "7563": null, "29075": null, "33214": null, "13254": null, "722": null, "4116": null, "7562": null, "13257": null, "33210": null, "636": null, "9629": null, "7558": null, "69394": null, "11169": null, "7692": null, "7573": null, "11158": null, "725": null, "28653": null, "11870": null, "50833": null, "216036": null, "44286": null, "2849": null, "7566": null, "12399": null, "32365": null, "526751": null, "11932": null, "4574": null, "16016": null, "6911": null, "13512": null, "151072": null, "2302": null, "216034": null, "24549": null, "51696": null, "8959": null, "7693": null, "5849": null, "11930": null, "2881": null, "6636": null, "11938": null, "11952": null, "13250": null, "91537": null, "33219": null, "2886": null, "23178": null, "19257": null, "8943": null, "4753": null, "1977": null, "32353": null, "190342": null, "168": null, "6881": null, "3931": null, "2871": null, "6915": null, "13258": null, "24548": null, "12630": null, "11960": null, "11955": null, "718": null, "6917": null, "10817": null, "7559": null, "7687": null, "1226": null, "2851": null, "37398": null, "37399": null, "24506": null, "70297": null, "33220": null, "114645": null, "230740": null, "1250": null, "3236": null, "7581": null, "8952": null, "54402": null, "151074": null, "20241": null, "19905": null}, "BILL": {"6578": null, "1226": null, "948": null, "1123": null, "855": null, "29432": null, "8490": null, "674": null, "4700": null, "2849": null, "273": null, "2836": null, "27633": null, "866": null, "1124": null, "2881": null, "6573": null, "10785": null, "12970": null, "27634": null, "2886": null, "22475": null, "1209": null, "1125": null, "18149": null, "5411": null, "278": null, "2855": null, "2862": null, "1027": null, "1176": null, "36382": null, "782": null, "784": null, "5960": null, "1782": null, "6867": null, "6636": null, "1977": null, "7439": null, "8515": null, "1816": null, "25052": null, "27632": null, "30563": null, "2824": null, "3914": null, "1144": null, "2871": null, "892": null, "826": null, "785": null, "5945": null, "1165": null, "7381": null, "3739": null, "8487": null, "2857": null, "3781": null, "2821": null, "25049": null, "1174": null, "1120": null, "2407": null, "2888": null, "2000": null, "7446": null, "8527": null, "843": null, "5483": null, "32352": null, "4056": null, "22486": null, "31961": null, "1193": null, "8489": null, "1134": null, "20516": null, "695": null, "1305": null, "1243": null, "1963": null, "2887": null, "2851": null, "800": null, "226": null, "7686": null, "768": null, "7393": null, "19623": null, "2858": null, "5978": null, "2419": null, "3054": null, "168": null, "74318": null, "3740": null, "4057": null, "17379": null, "26006": null}, "BINDER": {"1336": null, "1374": null, "1389": null, "3148": null, "1407": null, "1376": null, "1948": null, "3172": null, "3135": null, "4157": null, "10381": null, "1930": null, "3158": null, "3194": null, "3127": null, "1875": null, "3218": null, "5797": null, "3190": null, "3185": null, "3234": null, "3149": null, "3214": null, "1935": null, "3237": null, "2741": null, "3276": null, "2659": null, "3133": null, "10397": null, "1482": null, "3273": null, "1842": null, "1591": null, "3228": null, "3156": null, "10414": null, "1475": null, "2729": null, "3129": null, "1444": null, "1926": null, "3143": null, "3155": null, "3152": null, "5798": null, "1499": null, "1375": null, "3236": null, "3265": null, "3187": null, "2748": null, "3150": null, "4194": null, "3240": null, "8560": null, "3145": null, "3137": null, "3191": null, "14381": null, "105": null, "16391": null, "3131": null, "18497": null, "3144": null, "4146": null, "3189": null, "1919": null, "2700": null, "13920": null, "3243": null, "1406": null, "9346": null, "1830": null, "3253": null, "2642": null, "3125": null, "21704": null, "50824": null, "2718": null, "2643": null, "3167": null, "4180": null, "8054": null, "2660": null, "39459": null, "18498": null, "15416": null, "546": null, "14946": null, "14947": null, "996": null, "104": null, "9476": null, "10413": null, "24329": null, "39108": null, "126360": null, "1416": null, "1007": null}, "REINSTATEMENT NOTICE": {"13267": null, "22398": null, "61056": null, "2205": null, "19764": null, "2242": null, "24883": null, "5768": null, "3740": null, "2527": null, "17288": null, "20711": null, "19766": null, "75769": null, "8983": null, "6977": null, "1739": null, "33837": null, "35514": null, "1669": null, "11398": null, "1746": null, "9366": null, "2513": null, "10451": null, "2502": null, "2201": null, "43781": null, "69170": null, "1748": null, "11260": null, "4716": null, "10452": null, "7273": null, "27004": null, "8984": null, "11253": null, "25937": null, "651": null, "37492": null, "7271": null, "11399": null, "61055": null, "10439": null, "5381": null, "1640": null, "14988": null, "3741": null, "25911": null, "19709": null, "25910": null, "46003": null, "1777": null, "35519": null, "43790": null, "47510": null, "74895": null, "13289": null, "6858": null, "123": null, "1741": null, "5413": null, "27003": null, "1969": null, "3666": null, "3914": null, "818": null, "2532": null, "22794": null, "2042": null, "658": null, "63408": null, "122296": null, "22803": null, "10457": null, "11252": null, "2044": null, "11382": null, "31417": null, "55094": null, "7268": null, "1849": null, "2041": null, "264330": null, "1941": null, "20723": null, "13063": null, "37495": null, "6093": null, "17730": null, "20719": null, "33843": null, "5382": null, "9379": null, "17731": null, "24896": null, "29723": null, "46395": null, "93102": null, "93571": null}, "CHANGE ENDORSEMENT": {"2466": null, "2448": null, "7539": null, "2453": null, "2463": null, "2472": null, "2476": null, "2471": null, "7538": null, "2480": null, "2465": null, "2441": null, "2444": null, "2462": null, "2439": null, "1591": null, "2475": null, "2440": null, "2477": null, "12422": null, "37013": null, "2478": null, "1588": null, "12784": null, "1991": null, "2438": null, "2470": null, "2464": null, "12785": null, "37019": null, "89347": null, "2280": null, "531": null, "842": null, "2452": null, "2474": null, "29368": null, "29362": null, "29363": null, "37020": null, "56022": null, "93835": null, "14120": null, "4157": null, "8629": null, "51596": null, "3739": null, "14632": null, "22141": null, "1579": null, "6993": null, "413069": null, "473754": null, "590254": null, "37015": null, "278": null, "10414": null, "76196": null, "3143": null, "375880": null, "12267": null, "4561": null, "8642": null, "187390": null, "239995": null, "398017": null, "413073": null, "473753": null, "530237": null, "758611": null, "2659": null, "4540": null, "46808": null, "187402": null, "5410": null, "2748": null, "16779": null, "24722": null, "6021": null, "21353": null, "39125": null, "71833": null, "71834": null, "4548": null, "185431": null, "226": null, "225688": null, "244562": null, "295428": null, "354910": null, "413059": null, "530278": null, "577857": null, "758602": null, "758609": null, "758614": null, "761771": null, "765197": null, "73288": null, "7692": null}, "DECLARATION": {"50824": null, "126360": null, "1389": null, "1336": null, "1875": null, "2242": null, "3489": null, "50822": null, "470353": null, "133996": null, "1376": null, "2477": null, "1407": null, "1591": null, "438983": null, "575725": null, "10489": null, "1919": null, "16779": null, "20339": null, "2601": null, "4823": null, "1926": null, "418020": null, "1444": null, "235586": null, "2713": null, "20341": null, "1883": null, "20377": null, "18560": null, "287815": null, "512260": null, "512285": null, "999": null, "546": null, "10491": null, "37035": null, "3059": null, "3504": null, "21704": null, "283": null, "2704": null, "52641": null, "3237": null, "2659": null, "1956": null, "2631": null, "7108": null, "39459": null, "33711": null, "33712": null, "39470": null, "1954": null, "2858": null, "3295": null, "998": null, "26793": null, "6986": null, "287819": null, "2668": null, "2712": null, "128429": null, "256763": null, "256799": null, "256846": null, "1881": null, "2748": null, "53097": null, "14101": null, "6970": null, "6783": null, "75540": null, "104243": null, "11932": null, "1859": null, "3301": null, "1007": null, "11169": null, "4602": null, "1836": null, "9107": null, "3852": null, "2643": null, "10472": null, "1023": null, "5535": null, "10496": null, "2680": null, "3125": null, "1998": null, "84102": null, "246281": null, "50333": null, "166986": null, "4833": null, "47856": null, "44965": null, "39467": null, "3065": null}, "RETURNED CHECK": {"583190": null, "26793": null, "18353": null, "114339": null, "65932": null, "12504": null, "7245": null, "114347": null, "583192": null, "26822": null, "26785": null, "20318": null, "114336": null, "26784": null, "18350": null, "18347": null, "23913": null, "79173": null, "42405": null, "50451": null, "26779": null, "4951": null, "18384": null, "32707": null, "32715": null, "32716": null, "26805": null, "26800": null, "26782": null, "32710": null, "27143": null, "32713": null, "567483": null, "26786": null, "32721": null, "3159": null, "18346": null, "114344": null, "6175": null, "4960": null, "32706": null, "32709": null, "9570": null, "32720": null, "27090": null, "18334": null, "26808": null, "32169": null, "26778": null, "26843": null, "31643": null, "42404": null, "47116": null, "26781": null, "114346": null, "26801": null, "26798": null, "18335": null, "55165": null, "583197": null, "32711": null, "47446": null, "96019": null, "42752": null, "101230": null, "26780": null, "33763": null, "77799": null, "118895": null, "119826": null, "26803": null, "26804": null, "51229": null, "567481": null, "62028": null, "6320": null, "18381": null, "21999": null, "42767": null, "17798": null, "32714": null, "41616": null, "122550": null, "192157": null, "567485": null, "27124": null, "23891": null, "18361": null, "8654": null, "26845": null, "41615": null, "65209": null, "77796": null, "89740": null, "200974": null, "583196": null, "42403": null, "26829": null, "10668": null, "27153": null}, "NON-RENEWAL NOTICE": {"7667": null, "6821": null, "6816": null, "153763": null, "14303": null, "10778": null, "6857": null, "137789": null, "7649": null, "4328": null, "6828": null, "107004": null, "7646": null, "14769": null, "7642": null, "6833": null, "44527": null, "22297": null, "12630": null, "23173": null, "20258": null, "26539": null, "1289": null, "26540": null, "20740": null, "6781": null, "12677": null, "2115": null, "6850": null, "6820": null, "74510": null, "34516": null, "34519": null, "151413": null, "6825": null, "6835": null, "7570": null, "6854": null, "6858": null, "365755": null, "34517": null, "34844": null, "6093": null, "6852": null, "6847": null, "20807": null, "383747": null, "397779": null, "6817": null, "34518": null, "9011": null, "14343": null, "12628": null, "940": null, "603": null, "7648": null, "226": null, "29075": null, "9629": null, "937": null, "31051": null, "151173": null, "27373": null, "226508": null, "7643": null, "12003": null, "41796": null, "11100": null, "12680": null, "107483": null, "169996": null, "547376": null, "6824": null, "6851": null, "2888": null, "6819": null, "6818": null, "59929": null, "7565": null, "20260": null, "9033": null, "34521": null, "113001": null, "125232": null, "20259": null, "33030": null, "22436": null, "35611": null, "139184": null, "101984": null, "32305": null, "34860": null, "17695": null, "20256": null, "3785": null, "20726": null, "13040": null, "137801": null, "6827": null, "20263": null}, "APPLICATION": {"1591": null, "3041": null, "9591": null, "3474": null, "30098": null, "4891": null, "9589": null, "9609": null, "41634": null, "2668": null, "9562": null, "3504": null, "9598": null, "4210": null, "20358": null, "70997": null, "9554": null, "10419": null, "9614": null, "9488": null, "3029": null, "9529": null, "97310": null, "9613": null, "9612": null, "9484": null, "4634": null, "9504": null, "9491": null, "2811": null, "9568": null, "9551": null, "20357": null, "9592": null, "9415": null, "2847": null, "9547": null, "20342": null, "131923": null, "228542": null, "429287": null, "784703": null, "41115": null, "3489": null, "9586": null, "23182": null, "5978": null, "9560": null, "118421": null, "9626": null, "369909": null, "2855": null, "9507": null, "3502": null, "33572": null, "41627": null, "60002": null, "80997": null, "153165": null, "228543": null, "784704": null, "13769": null, "23085": null, "20341": null, "41004": null, "7444": null, "9608": null, "9605": null, "6964": null, "9514": null, "6921": null, "9550": null, "55824": null, "21999": null, "9593": null, "105": null, "9494": null, "23188": null, "3508": null, "9541": null, "131931": null, "138787": null, "153188": null, "189146": null, "286733": null, "443833": null, "553738": null, "602004": null, "784715": null, "17817": null, "9508": null, "179375": null, "23189": null, "9552": null, "9509": null, "17588": null, "20359": null, "70999": null, "6951": null, "20362": null}, "INTENT TO CANCEL NOTICE": {"3932": null, "336899": null, "3934": null, "3908": null, "39108": null, "3946": null, "46235": null, "20957": null, "69265": null, "125839": null, "3905": null, "46234": null, "69274": null, "3666": null, "3922": null, "18754": null, "77722": null, "3917": null, "3940": null, "20964": null, "19824": null, "19825": null, "32432": null, "261628": null, "18621": null, "3931": null, "192014": null, "3916": null, "763447": null, "3948": null, "57793": null, "114591": null, "4028": null, "674": null, "5762": null, "3904": null, "201553": null, "19860": null, "18542": null, "6867": null, "250852": null, "18630": null, "92152": null, "233130": null, "323382": null, "460462": null, "581388": null, "604946": null, "336975": null, "633338": null, "19851": null, "31884": null, "167887": null, "262441": null, "19856": null, "87818": null, "592482": null, "11169": null, "855": null, "2861": null, "1746": null, "651": null, "54891": null, "1149": null, "21812": null, "7598": null, "11932": null, "9232": null, "230904": null, "19871": null, "227724": null, "167889": null, "87822": null, "184791": null, "13433": null, "388124": null, "199397": null, "199400": null, "312654": null, "25496": null, "25629": null, "25632": null, "18196": null, "330818": null, "18649": null, "12648": null, "6885": null, "179283": null, "19861": null, "19868": null, "150951": null, "153959": null, "206067": null, "206069": null, "206070": null, "267441": null, "321356": null, "330816": null, "337052": null, "337055": null}, "BILL BINDER": {"3054": null, "168": null, "21826": null, "22984": null, "53121": null, "82527": null, "74539": null, "105": null, "90016": null, "67750": null, "8944": null, "4700": null, "23071": null, "388971": null, "388974": null, "9605": null, "12995": null, "82520": null, "12983": null, "2931": null, "224542": null, "265615": null, "87358": null, "866": null, "289": null, "21967": null, "14620": null, "24177": null, "9607": null, "948": null, "21823": null, "100899": null, "9090": null, "27260": null, "21746": null, "552": null, "9608": null, "53082": null, "33033": null, "9568": null, "23075": null, "14583": null, "21841": null, "21390": null, "3044": null, "14589": null, "14588": null, "1591": null, "22987": null, "1174": null, "23076": null, "14368": null, "23072": null, "1830": null, "388423": null, "792109": null, "28269": null, "5441": null, "27255": null, "23033": null, "12504": null, "23294": null, "22977": null, "14565": null, "14585": null, "3504": null, "23085": null, "6986": null, "13003": null, "14586": null, "546309": null, "690959": null, "3043": null, "100900": null, "6687": null, "4554": null, "68244": null, "3502": null, "16779": null, "9554": null, "4351": null, "33409": null, "3029": null, "10069": null, "23009": null, "100896": null, "13473": null, "3058": null, "42980": null, "4751": null, "87357": null, "100898": null, "5616": null, "24220": null, "84682": null, "23041": null, "100892": null, "21820": null, "185320": null, "265599": null}}